{
  "title": "Lecture 9.4 Basic Array Example - Iterating through an array",
  "summary": "Basic Array Example COS1004 Lecture 9.4 Iterating though an array •Consider this psuedocode –what is it doing ? numarray[10]: {3, 2, 5, 3, 5, 6, 1, 2, 4, 9} sum = 0 i = 0 while(i < 10)do sum = sum + numarray[i] i = i + 1; end while Iteratin",
  "widget_type": "none",
  "position": 4,
  "is_published": true,
  "content_html": "<pre class=\"source-text\">Basic Array Example\n\n         COS1004 Lecture 9.4\n\nIterating though an array\n\n•Consider this psuedocode –what is it doing ?\nnumarray[10]: {3, 2, 5, 3, 5, 6, 1, 2, 4, 9}\nsum = 0\ni = 0\nwhile(i   &lt; 10)do\n     sum = sum + numarray[i]\n      i  = i  + 1;\nend while\n\nIterating though an array\n\n•Consider this psuedo   code – what is it doing ?\nnumarray[10]: {3, 2, 5, 3, 5, 6, 1, 2, 4, 9}\nsum = 0\ni  = 0\nwhile(i     &lt; 10)do\n      sum = sum + numarray[i]\n       i  = i    + 1;\nend while\n                        It’s defining an array of 10 integers and summing the values\n\nIterating though an array\n\n\n\n• Lets do this in Assembly code\n• First, define the array with some labels:\n\narraysize: 40\nnumarray: .Word 3\n 2\n 5\n 3\n 5\n 6\n 1\n 2\n 4\n 9\n\nIterating though an array\n\n•Lets do this in Assembly code\n•Next, initialise some registers:\n\n\nMOV R0, #numarray\nMOV R1, #0    // index\nMOV R2, #0          // sum\nHALT\narraysize: 40\nnumarray: .Word 3  2  5 3 5  6  1 2 4 9   //                -\nthese should be one per line in actual code\n\nIterating though an array\n\n\n• Lets do this in Assembly code\n• Next, setup a label and conditional branch for looping\n\n\n\nMOV R0, #numarray\nMOV R1, #0    // index\nMOV R2, #0        // sum\narrayloop:\nCMP R1, #arraysize\nBLT arrayloop\nHALT\narraysize: 40            // 10 * 4 bytes\nnumarray: .Word 3  2  5 3 5  6  1 2 4 9   // -               these should be one per\nline in actual code\n\nIterating though an array\n\n\n\n• Lets do this in Assembly code\n• Next, insert code to access each item in array and increment index\n\n\n\nMOV R0, #numarray\nMOV R1, #0    // index\nMOV R2, #0              // sum\narrayloop:\nLDR R3, [R0 + R1]                 // access array item at current index (R1)\nADD R1, R1, #4                                // increment index to next 32 bit word\nCMP R1, #arraysize\nBLT arrayloop\nHALT\narraysize: 40   // 10 * 4 bytes\nnumarray: .Word 3  2       5 3 5  6  1 2 4 9   // -        these should be one per line in actual code\n\nIterating though an array\n\n\n\n• Lets do this in Assembly code\n• Next, insert code to access each item in array and increment index\n\n\n\nMOV R0, #numarray\nMOV R1, #0    // index\nMOV R2, #0           // sum\narrayloop:\nLDR R3, [R0 + R1]                       // access array item at current index (R1)\nADD R1, R1, #4                           // increment index to next 32 bit word\nCMP R1, #arraysize\nBLT arrayloop\nHALT\narraysize: 40  // 10 * 4 bytes\nnumarray: .Word 3 2 5 3 5 6 1 2 4 9            // -    these should be one per line in actual code\n\nIterating though an array\n\n\n\n• Lets do this in Assembly code\n• Finally, add each value to the accumulating “sum”\n\nMOV R0, #numarray\nMOV R1, #0    // index\nMOV R2, #0    // sum accumulator\narrayloop:\nLDR R3, [R0 + R1]                        // access array item at current index (R1)\nADD R2, R2, R3                           // add value to accumulator (R2)\nADD R1, R1, #4                           // increment index to next 32 bit word\nCMP R1, #arraysize\nBLT arrayloop\nHALT\narraysize: 40                // 10 * 4 bytes\nnumarray: .Word 3 2 5 3 5 6 1 2 4 9 -           these should be one per line in actual code</pre>",
  "exercises": []
}
